aliyunsdkocr/__init__.py
aliyunsdkocr/endpoint.py
aliyunsdkocr/request/__init__.py
aliyunsdkocr/request/v20191230/GetAsyncJobResultRequest.py
aliyunsdkocr/request/v20191230/RecognizeBankCardRequest.py
aliyunsdkocr/request/v20191230/RecognizeBusinessLicenseRequest.py
aliyunsdkocr/request/v20191230/RecognizeCharacterRequest.py
aliyunsdkocr/request/v20191230/RecognizeDriverLicenseRequest.py
aliyunsdkocr/request/v20191230/RecognizeDrivingLicenseRequest.py
aliyunsdkocr/request/v20191230/RecognizeIdentityCardRequest.py
aliyunsdkocr/request/v20191230/RecognizeLicensePlateRequest.py
aliyunsdkocr/request/v20191230/RecognizePdfRequest.py
aliyunsdkocr/request/v20191230/RecognizeQrCodeRequest.py
aliyunsdkocr/request/v20191230/RecognizeQuotaInvoiceRequest.py
aliyunsdkocr/request/v20191230/RecognizeTableRequest.py
aliyunsdkocr/request/v20191230/RecognizeTaxiInvoiceRequest.py
aliyunsdkocr/request/v20191230/RecognizeTicketInvoiceRequest.py
aliyunsdkocr/request/v20191230/RecognizeTrainTicketRequest.py
aliyunsdkocr/request/v20191230/RecognizeVATInvoiceRequest.py
aliyunsdkocr/request/v20191230/RecognizeVINCodeRequest.py
aliyunsdkocr/request/v20191230/RecognizeVideoCharacterRequest.py
aliyunsdkocr/request/v20191230/__init__.py
aliyun_python_sdk_ocr-1.0.25.dist-info/LICENSE
aliyun_python_sdk_ocr-1.0.25.dist-info/METADATA
aliyun_python_sdk_ocr-1.0.25.dist-info/WHEEL
aliyun_python_sdk_ocr-1.0.25.dist-info/top_level.txt
aliyun_python_sdk_ocr-1.0.25.dist-info/RECORD
